{"nodes": [{"id": "frontend_readme_assets_architecture_png", "label": "Architecture Diagram", "file_type": "image", "source_file": "frontend/readme-assets/architecture.png", "source_location": null, "source_url": null, "captured_at": null, "author": null, "contributor": null}], "edges": [{"source": "frontend_readme_assets_architecture_png", "target": "users_browser", "relation": "depicts", "confidence": "EXTRACTED", "confidence_score": 1.0, "source_file": "frontend/readme-assets/architecture.png", "source_location": null, "weight": 1.0}, {"source": "frontend_readme_assets_architecture_png", "target": "vercel_platform", "relation": "depicts", "confidence": "EXTRACTED", "confidence_score": 1.0, "source_file": "frontend/readme-assets/architecture.png", "source_location": null, "weight": 1.0}, {"source": "frontend_readme_assets_architecture_png", "target": "nextjs_frontend", "relation": "depicts", "confidence": "EXTRACTED", "confidence_score": 1.0, "source_file": "frontend/readme-assets/architecture.png", "source_location": null, "weight": 1.0}, {"source": "frontend_readme_assets_architecture_png", "target": "nextjs_api_routes", "relation": "depicts", "confidence": "EXTRACTED", "confidence_score": 1.0, "source_file": "frontend/readme-assets/architecture.png", "source_location": null, "weight": 1.0}, {"source": "frontend_readme_assets_architecture_png", "target": "firebase_auth", "relation": "depicts", "confidence": "EXTRACTED", "confidence_score": 1.0, "source_file": "frontend/readme-assets/architecture.png", "source_location": null, "weight": 1.0}, {"source": "frontend_readme_assets_architecture_png", "target": "google_gemini_ai", "relation": "depicts", "confidence": "EXTRACTED", "confidence_score": 1.0, "source_file": "frontend/readme-assets/architecture.png", "source_location": null, "weight": 1.0}, {"source": "users_browser", "target": "vercel_platform", "relation": "requests", "confidence": "EXTRACTED", "confidence_score": 1.0, "source_file": "frontend/readme-assets/architecture.png", "source_location": null, "weight": 1.0}, {"source": "vercel_platform", "target": "nextjs_frontend", "relation": "hosts", "confidence": "EXTRACTED", "confidence_score": 1.0, "source_file": "frontend/readme-assets/architecture.png", "source_location": null, "weight": 1.0}, {"source": "nextjs_frontend", "target": "nextjs_api_routes", "relation": "calls", "confidence": "EXTRACTED", "confidence_score": 1.0, "source_file": "frontend/readme-assets/architecture.png", "source_location": null, "weight": 1.0}, {"source": "nextjs_api_routes", "target": "google_gemini_ai", "relation": "calls", "confidence": "EXTRACTED", "confidence_score": 1.0, "source_file": "frontend/readme-assets/architecture.png", "source_location": null, "weight": 1.0}, {"source": "nextjs_api_routes", "target": "firebase_auth", "relation": "calls", "confidence": "EXTRACTED", "confidence_score": 1.0, "source_file": "frontend/readme-assets/architecture.png", "source_location": null, "weight": 1.0}, {"source": "nextjs_frontend", "target": "firebase_auth", "relation": "requests", "confidence": "INFERRED", "confidence_score": 0.8, "source_file": "frontend/readme-assets/architecture.png", "source_location": null, "weight": 1.0}, {"source": "nextjs_frontend", "target": "react_components", "relation": "uses", "confidence": "EXTRACTED", "confidence_score": 1.0, "source_file": "frontend/readme-assets/architecture.png", "source_location": null, "weight": 1.0}, {"source": "nextjs_api_routes", "target": "backend_logic", "relation": "provides", "confidence": "EXTRACTED", "confidence_score": 1.0, "source_file": "frontend/readme-assets/architecture.png", "source_location": null, "weight": 1.0}], "hyperedges": [{"id": "skillsphere_architecture", "label": "SkillSphere Architecture Components", "nodes": ["users_browser", "vercel_platform", "nextjs_frontend", "nextjs_api_routes", "firebase_auth", "google_gemini_ai"], "relation": "form", "confidence": "EXTRACTED", "confidence_score": 1.0, "source_file": "frontend/readme-assets/architecture.png"}]}